{
  "contactSection": {
    "tag": "Get In Touch",
    "title": "Ready to Transform Your IT?",
    "subtitle": "Tell us about your project. We respond within 24 hours with a clear, actionable plan.",
    "cards": [
      {
        "icon": "email",
        "label": "Email",
        "valueKey": "email",
        "linkType": "email"
      },
      {
        "icon": "phone",
        "label": "Phone",
        "valueKey": "phone",
        "linkType": "tel"
      },
      {
        "icon": "whatsapp",
        "label": "WhatsApp",
        "valueKey": "whatsapp",
        "linkType": "whatsapp"
      },
      {
        "icon": "mapPin",
        "label": "Location",
        "valueKey": "location"
      }
    ]
  },
  "servicesSection": {
    "tag": "What We Offer",
    "title": "Our Core Services",
    "subtitle": "Five capability areas, twelve specializations — end-to-end IT solutions built around your business goals. Tap a category to see what's inside.",
    "categories": [
      {
        "id": "01",
        "title": "Networking & Infrastructure",
        "subtitle": "Design, cabling, and management for networks that just work",
        "areas": [
          {
            "title": "Cabling Solutions",
            "items": [
              "Design, installation & maintenance of networks",
              "End-to-end structured cable systems",
              "CAT5e, CAT6, CAT6A & CAT6+ copper cabling",
              "Multi-mode & single-mode fiber optic cabling",
              "Series 6 & Series 11 coaxial cabling",
              "CCTV cabling & installation"
            ]
          },
          {
            "title": "Network Infrastructure",
            "items": [
              "LAN/WAN design, installation & configuration",
              "Wireless & connectivity solutions",
              "VoIP solutions",
              "Load balancing & bandwidth management",
              "Remote data center management"
            ]
          }
        ]
      },
      {
        "id": "02",
        "title": "Security Solutions",
        "subtitle": "Physical and digital protection, integrated",
        "areas": [
          {
            "title": "CCTV Systems",
            "items": [
              "Analog & IP cameras (indoor & outdoor)",
              "CMOS, CCD & HD cameras",
              "NVR & DVR recorders (4–24 channels)",
              "Full-time & motion-triggered recording",
              "Online monitoring from anywhere worldwide"
            ]
          },
          {
            "title": "Entry & Access Systems",
            "items": [
              "Biometric & card-based access control",
              "Automated alerts & triggering features",
              "Voice & VoIP-based video intercoms",
              "Door phone systems (audio & video)",
              "Integration with CCTV & security systems"
            ]
          },
          {
            "title": "Cybersecurity",
            "items": [
              "Firewall setup, configuration & management",
              "Endpoint protection & antivirus deployment",
              "Vulnerability assessments & penetration testing",
              "Data loss prevention (DLP) solutions",
              "Compliance support (ISO 27001, GDPR, NCA)",
              "Incident response & recovery planning"
            ]
          }
        ]
      },
      {
        "id": "03",
        "title": "Software & Digital",
        "subtitle": "Custom software, websites, and apps built around your business",
        "areas": [
          {
            "title": "Software Solutions",
            "items": [
              "Custom business application development",
              "ERP & CRM system integration",
              "Process automation & workflow tools",
              "Software consulting & architecture",
              "Legacy system modernisation"
            ]
          },
          {
            "title": "Web Development",
            "items": [
              "Business websites & landing pages",
              "E-commerce platforms & online stores",
              "Web portals & dashboards",
              "CMS integration (WordPress, custom)",
              "SEO-ready & mobile-responsive design"
            ]
          },
          {
            "title": "Mobile App Development",
            "items": [
              "Native iOS & Android app development",
              "Cross-platform apps (Flutter, React Native)",
              "UI/UX design & prototyping",
              "App Store & Play Store publishing",
              "Post-launch maintenance & updates"
            ]
          }
        ]
      },
      {
        "id": "04",
        "title": "Cloud & Email Solutions",
        "subtitle": "Infrastructure and communication that scales with you",
        "areas": [
          {
            "title": "Cloud Solutions",
            "items": [
              "Cloud migration & strategy planning",
              "AWS, Azure & Google Cloud setup",
              "Cloud storage & backup solutions",
              "Hybrid & multi-cloud environments",
              "Ongoing cloud monitoring & optimisation"
            ]
          },
          {
            "title": "Email Solutions",
            "items": [
              "Business email hosting & setup",
              "Microsoft 365 & Google Workspace",
              "Email migration & domain configuration",
              "Spam filtering & security policies",
              "Email backup & archiving solutions"
            ]
          }
        ]
      },
      {
        "id": "05",
        "title": "IT Support & Consultancy",
        "subtitle": "Strategic guidance and always-on support",
        "areas": [
          {
            "title": "IT Consultancy",
            "items": [
              "IT infrastructure audits & assessments",
              "Digital transformation strategy & roadmaps",
              "Technology budgeting & procurement advice",
              "Vendor selection & management support",
              "Business continuity & disaster recovery planning"
            ]
          },
          {
            "title": "Reliable IT Support",
            "items": [
              "24/7 help desk (chat, email, remote)",
              "Onsite IT support & troubleshooting",
              "Preventative maintenance & monitoring",
              "Customized IT support plans"
            ]
          }
        ]
      }
    ]
  },
  "projectsSection": {
    "tag": "Our Work",
    "title": "Successfully Delivered Projects",
    "subtitle": "Real platforms we built for growing businesses from fleet operations to full e-commerce management, designed to save time and drive revenue.",
    "projects": [
      {
        "name": "FleetDesk",
        "category": "Car Rental Management System",
        "tagline": "Run your entire rental shop from one smart dashboard",
        "description": "FleetDesk is a complete online car rental management platform that gives shop owners full control over their fleet, bookings, finances, and team — without spreadsheets or guesswork.",
        "highlights": [
          "Manage every vehicle and see available days at a glance",
          "Revenue, expenses, and profit analytics in real time",
          "Employee management and office expense tracking",
          "Live rental tracking with service alerts and notifications"
        ],
        "screens": [
          {
            "label": "Analytics Dashboard",
            "src": "/projects/fleetdesk.png",
            "alt": "FleetDesk analytics dashboard showing revenue, bookings, and fleet utilization"
          }
        ]
      },
      {
        "name": "Fasa Products",
        "category": "E-Commerce & Business Management",
        "websiteUrl": "https://fasafoods.com/",
        "websiteLabel": "fasafoods.com",
        "tagline": "Live e-commerce store with a powerful admin back office",
        "description": "A full online business platform built for Fasa Products — a customer-facing storefront at fasafoods.com paired with an admin system to manage orders, inventory, and sales insights in one place.",
        "highlights": [
          "Live storefront at fasafoods.com with product catalog and special offers",
          "Unified orders dashboard for pending, processing, and delivered orders",
          "Inventory management with low-stock notifications",
          "Best-selling product insights tracked by period"
        ],
        "screens": [
          {
            "label": "Online Store",
            "src": "/projects/fasa-storefront.png",
            "alt": "Fasa Products e-commerce website at fasafoods.com showing product catalog and special offers"
          },
          {
            "label": "Orders Dashboard",
            "src": "/projects/fasa-orders-dashboard.png",
            "alt": "Fasa Products orders management dashboard with order tracking and status updates"
          }
        ]
      }
    ]
  },
  "supportSection": {
    "tag": "Always Here for You",
    "title": "World-Class IT Support",
    "subtitle": "AnyTech understands how critical your IT systems are. We pride ourselves on always-available, best-in-class helpdesk and onsite support.",
    "features": [
      {
        "icon": "monitor",
        "title": "Help Desk Support",
        "description": "Continuous service ensuring your critical IT systems and applications are always up and running. Problems resolved quickly by knowledgeable technicians.",
        "items": [
          "24×7 helpdesk support, 365 days a year",
          "Chat-based and email-based support",
          "Remote support for email, servers, PCs & networks",
          "Fast handling of IT-related issues",
          "Customized solutions per client need"
        ]
      },
      {
        "icon": "wrench",
        "title": "Onsite Support",
        "description": "When remote support isn't enough, AnyTech's onsite team is always available to bring your network back online with a fully managed, hands-on approach.",
        "items": [
          "Cabling & Wireless Solutions onsite",
          "Recurring on-site services & project support",
          "Full-Time Onsite IT Support (daily/weekly/monthly)",
          "Seasonal Onsite IT Support for peak periods",
          "On-site end-user desktop support"
        ]
      },
      {
        "icon": "shieldCheck",
        "title": "Preventative Maintenance & Updates",
        "description": "Proactive monitoring and scheduled maintenance so you never face unexpected downtime or system failures.",
        "items": [
          "24/7 real-time monitoring & automated alerts",
          "Regular system health checks",
          "Software & firmware updates",
          "Day-to-day management support"
        ]
      }
    ],
    "card": {
      "title": "Always Available. Always Reliable.",
      "description": "Our dedicated support team is standing by around the clock to ensure your business never skips a beat.",
      "availability": [
        "24 / 7 / 365 Help Desk",
        "Remote & Onsite Response",
        "Real-Time Monitoring",
        "Preventative Maintenance",
        "Customized SLA Plans"
      ],
      "cta": "Contact Support"
    }
  },
  "navLinks": [
    {
      "href": "#vision",
      "label": "About"
    },
    {
      "href": "#services",
      "label": "Services"
    },
    {
      "href": "#support",
      "label": "Support"
    },
    {
      "href": "#contact",
      "label": "Contact"
    }
  ],
  "heroFeatures": [
    {
      "icon": "network",
      "label": "Network & Infrastructure"
    },
    {
      "icon": "cloud",
      "label": "Cloud Solutions"
    },
    {
      "icon": "software",
      "label": "Software & Web Development"
    }
  ],
  "hero": {
    "badge": "AnyTech Solution — IT, Software & Network Solutions Specialists",
    "title": "Your Dream Is",
    "titleHighlight": "Our Mission",
    "description": "AnyTech Solutions delivers custom software, mobile apps, and robust network infrastructure paired with reliable support and seamless cloud migration to build smart, affordable technology that drives businesses forward, worldwide.",
    "taglineQuote": "\"To become a leading IT solutions facilitator in the global marketplace\""
  },
  "company": {
    "legalName": "AnyTech Solution (PVT) Ltd",
    "copyright": "© 2026 AnyTech Solution (PVT) Ltd. All rights reserved.",
    "nameHighlight": "Any",
    "name": "Anytech Solution",
    "phone": "+94 70 660 3503",
    "tagline": "Your Dream is Our Mission",
    "whatsapp": "+94 70 660 3503",
    "location": "Sri Lanka",
    "email": "info@anytech.lk"
  },
  "socialLinks": [
    {
      "icon": "facebook",
      "label": "Facebook",
      "href": "https://www.facebook.com/"
    },
    {
      "icon": "linkedin",
      "label": "LinkedIn",
      "href": "https://www.linkedin.com/"
    },
    {
      "icon": "instagram",
      "label": "Instagram",
      "href": "https://www.instagram.com/"
    },
    {
      "icon": "whatsapp",
      "label": "WhatsApp",
      "href": "https://wa.me/94706603503"
    },
    {
      "icon": "email",
      "label": "Email",
      "href": "mailto:info@anytech.lk"
    }
  ],
  "visionSection": {
    "tag": "Who We Are",
    "title": "Vision, Mission & Values",
    "subtitle": "We exist to enhance business growth through technology solutions that create real, lasting competitive advantage.",
    "cards": [
      {
        "icon": "target",
        "title": "Our Vision",
        "description": "To become a leading IT solutions facilitator in the global marketplace through providing well-reliable and quality service."
      },
      {
        "icon": "rocket",
        "title": "Our Mission",
        "description": "To serve our customers with the best innovative IT solutions at affordable prices, while keeping a healthy and long-term relationship with them."
      },
      {
        "icon": "globe",
        "title": "Our Commitment",
        "description": "To enhance business growth through technology, network, and hardware solutions that deliver market-defining quality and reliable competitive advantage to customers around the globe."
      }
    ]
  },
  "stats": [
    {
      "value": "200",
      "suffix": "+",
      "label": "Projects Delivered",
      "icon": "projects"
    },
    {
      "value": "98",
      "suffix": "%",
      "label": "Client Satisfaction",
      "icon": "satisfaction"
    },
    {
      "value": "24",
      "suffix": "/7",
      "label": "Support Coverage",
      "icon": "support247"
    },
    {
      "value": "10",
      "suffix": "+",
      "label": "Years of Experience",
      "icon": "experience"
    }
  ]
}
